mcp_server.py
bing_flights_mcp-1.0.1.dist-info/licenses/LICENSE
bing_flights_scraper/__init__.py
bing_flights_scraper/scraper.py
bing_flights_mcp-1.0.1.dist-info/METADATA
bing_flights_mcp-1.0.1.dist-info/WHEEL
bing_flights_mcp-1.0.1.dist-info/entry_points.txt
bing_flights_mcp-1.0.1.dist-info/top_level.txt
bing_flights_mcp-1.0.1.dist-info/RECORD
