Metadata-Version: 2.4
Name: bing-flights-mcp
Version: 1.0.1
Summary: MCP server for searching flights on Bing Flights
Author-email: Peter Che <chonseng38@gmail.com>
License-Expression: MIT
Project-URL: Homepage, https://github.com/chonseng/bing-flights-mcp
Requires-Python: >=3.10
License-File: LICENSE
Requires-Dist: fastmcp>=0.1.0
Requires-Dist: playwright>=1.40.0
Requires-Dist: python-dateutil>=2.8.2
Dynamic: license-file
